cbrkit/__init__.py
cbrkit/__main__.py
cbrkit/adapt/__init__.py
cbrkit/adapt/attribute_value.py
cbrkit/adapt/generic.py
cbrkit/adapt/numbers.py
cbrkit/adapt/strings.py
cbrkit/api.py
cbrkit/cli.py
cbrkit/constants.py
cbrkit/cycle.py
cbrkit/dumpers.py
cbrkit/eval/__init__.py
cbrkit/eval/common.py
cbrkit/eval/retrieval.py
cbrkit/helpers.py
cbrkit/loaders.py
cbrkit/model/__init__.py
cbrkit/model/graph.py
cbrkit/model/result.py
cbrkit/py.typed
cbrkit/retrieval/__init__.py
cbrkit/retrieval/apply.py
cbrkit/retrieval/build.py
cbrkit/retrieval/rerank.py
cbrkit/reuse/__init__.py
cbrkit/reuse/apply.py
cbrkit/reuse/build.py
cbrkit/sim/__init__.py
cbrkit/sim/aggregator.py
cbrkit/sim/attribute_value.py
cbrkit/sim/collections.py
cbrkit/sim/embed.py
cbrkit/sim/generic.py
cbrkit/sim/graphs/__init__.py
cbrkit/sim/graphs/alignment.py
cbrkit/sim/graphs/astar.py
cbrkit/sim/graphs/brute_force.py
cbrkit/sim/graphs/common.py
cbrkit/sim/graphs/dfs.py
cbrkit/sim/graphs/greedy.py
cbrkit/sim/graphs/lap.py
cbrkit/sim/graphs/precompute.py
cbrkit/sim/graphs/qap.py
cbrkit/sim/graphs/vf2.py
cbrkit/sim/numbers.py
cbrkit/sim/pooling.py
cbrkit/sim/strings.py
cbrkit/sim/taxonomy.py
cbrkit/sim/wrappers.py
cbrkit/synthesis/__init__.py
cbrkit/synthesis/apply.py
cbrkit/synthesis/build.py
cbrkit/synthesis/model.py
cbrkit/synthesis/prompts.py
cbrkit/synthesis/providers/__init__.py
cbrkit/synthesis/providers/anthropic.py
cbrkit/synthesis/providers/cohere.py
cbrkit/synthesis/providers/google.py
cbrkit/synthesis/providers/instructor.py
cbrkit/synthesis/providers/model.py
cbrkit/synthesis/providers/ollama.py
cbrkit/synthesis/providers/openai_agents.py
cbrkit/synthesis/providers/openai_completions.py
cbrkit/synthesis/providers/pydantic_ai.py
cbrkit/synthesis/providers/wrappers.py
cbrkit/system.py
cbrkit/typing.py
cbrkit-0.28.5.dist-info/WHEEL
cbrkit-0.28.5.dist-info/entry_points.txt
cbrkit-0.28.5.dist-info/METADATA
cbrkit-0.28.5.dist-info/RECORD
