Metadata-Version: 2.3
Name: cbrkit
Version: 0.28.5
Summary: Customizable Case-Based Reasoning (CBR) toolkit for Python with a built-in API and CLI
Keywords: cbr,case-based reasoning,api,similarity,nlp,retrieval,cli,tool,library
Author: Mirko Lenz
Author-email: Mirko Lenz <mirko@mirkolenz.com>
Classifier: Development Status :: 4 - Beta
Classifier: Environment :: Console
Classifier: Framework :: Pytest
Classifier: Intended Audience :: Developers
Classifier: Intended Audience :: Science/Research
Classifier: License :: OSI Approved :: MIT License
Classifier: Natural Language :: English
Classifier: Operating System :: OS Independent
Classifier: Programming Language :: Python :: 3.12
Classifier: Programming Language :: Python :: 3.13
Classifier: Programming Language :: Python :: 3
Classifier: Topic :: Scientific/Engineering :: Artificial Intelligence
Classifier: Topic :: Scientific/Engineering :: Information Analysis
Classifier: Topic :: Software Development :: Libraries :: Python Modules
Classifier: Topic :: Utilities
Classifier: Typing :: Typed
Requires-Dist: frozendict>=2,<3
Requires-Dist: numpy>=1,<2 ; platform_machine == 'x86_64' and sys_platform == 'darwin'
Requires-Dist: numpy>=2,<3 ; platform_machine != 'x86_64' or sys_platform != 'darwin'
Requires-Dist: orjson>=3,<4
Requires-Dist: pandas>=2,<3
Requires-Dist: polars>=1,<2
Requires-Dist: pydantic>=2,<3
Requires-Dist: pyyaml>=6,<7
Requires-Dist: rich>=13,<15
Requires-Dist: rtoml>=0.12,<1
Requires-Dist: scipy>=1,<2
Requires-Dist: xmltodict>=1,<2
Requires-Dist: cbrkit[api,cli,eval,graphs,graphviz,llm,nlp,timeseries,transformers] ; extra == 'all'
Requires-Dist: cbrkit[cli] ; extra == 'api'
Requires-Dist: fastapi>=0.100,<1 ; extra == 'api'
Requires-Dist: pydantic-settings>=2,<3 ; extra == 'api'
Requires-Dist: python-multipart>=0.0.15,<1 ; extra == 'api'
Requires-Dist: uvicorn[standard]>=0.30,<1 ; extra == 'api'
Requires-Dist: fastmcp>=2,<3 ; extra == 'api'
Requires-Dist: jsonref>=1,<2 ; extra == 'api'
Requires-Dist: chonkie>=1,<2 ; extra == 'chunking'
Requires-Dist: typer>=0.9,<1 ; extra == 'cli'
Requires-Dist: ranx>=0.3,<1 ; extra == 'eval'
Requires-Dist: networkx>=3,<4 ; extra == 'graphs'
Requires-Dist: rustworkx>=0.15,<1 ; extra == 'graphs'
Requires-Dist: pygraphviz>=1,<2 ; extra == 'graphviz'
Requires-Dist: cohere>=5,<6 ; extra == 'llm'
Requires-Dist: voyageai>=0.3,<1 ; extra == 'llm'
Requires-Dist: ollama>=0.3,<1 ; extra == 'llm'
Requires-Dist: openai>=1,<2 ; extra == 'llm'
Requires-Dist: tiktoken>=0.8,<1 ; extra == 'llm'
Requires-Dist: anthropic>=0.40,<1 ; extra == 'llm'
Requires-Dist: google-genai>=1,<2 ; extra == 'llm'
Requires-Dist: instructor>=1,<2 ; extra == 'llm'
Requires-Dist: openai-agents>=0.2,<1 ; extra == 'llm'
Requires-Dist: pydantic-ai-slim>=1,<2 ; extra == 'llm'
Requires-Dist: bm25s[core,stem]>=0.2,<1 ; extra == 'nlp'
Requires-Dist: levenshtein>=0.23,<0.26 ; platform_machine == 'x86_64' and sys_platform == 'darwin' and extra == 'nlp'
Requires-Dist: levenshtein>=0.26,<1 ; (platform_machine != 'x86_64' and extra == 'nlp') or (sys_platform != 'darwin' and extra == 'nlp')
Requires-Dist: nltk>=3,<4 ; extra == 'nlp'
Requires-Dist: spacy>=3.7,<3.8 ; platform_machine == 'x86_64' and sys_platform == 'darwin' and extra == 'nlp'
Requires-Dist: spacy>=3.8,<4 ; (platform_machine != 'x86_64' and extra == 'nlp') or (sys_platform != 'darwin' and extra == 'nlp')
Requires-Dist: minineedle>=3,<4 ; extra == 'timeseries'
Requires-Dist: sentence-transformers>=3,<6 ; extra == 'transformers'
Requires-Dist: torch>=2.2,<2.3 ; platform_machine == 'x86_64' and sys_platform == 'darwin' and extra == 'transformers'
Requires-Dist: torch>=2.5,<3 ; (platform_machine != 'x86_64' and extra == 'transformers') or (sys_platform != 'darwin' and extra == 'transformers')
Requires-Dist: transformers>=4,<5 ; extra == 'transformers'
Requires-Python: >=3.12
Project-URL: Changelog, https://github.com/wi2trier/cbrkit/releases
Project-URL: Documentation, https://wi2trier.github.io/cbrkit/
Project-URL: Issues, https://github.com/wi2trier/cbrkit/issues
Project-URL: Repository, https://github.com/wi2trier/cbrkit
Provides-Extra: all
Provides-Extra: api
Provides-Extra: chunking
Provides-Extra: cli
Provides-Extra: eval
Provides-Extra: graphs
Provides-Extra: graphviz
Provides-Extra: llm
Provides-Extra: nlp
Provides-Extra: timeseries
Provides-Extra: transformers
